muzero_baseline/ProgressBar.py
muzero_baseline/__init__.py
muzero_baseline/diagnose_model.py
muzero_baseline/models.py
muzero_baseline/muzero.py
muzero_baseline/replay_buffer.py
muzero_baseline/self_play.py
muzero_baseline/shared_storage.py
muzero_baseline/trainer.py
muzero_baseline/games/__init__.py
muzero_baseline/games/abstract_game.py
muzero_baseline/games/atari.py
muzero_baseline/games/breakout.py
muzero_baseline/games/cartpole.py
muzero_baseline/games/connect4.py
muzero_baseline/games/gomoku.py
muzero_baseline/games/gridworld.py
muzero_baseline/games/lunarlander.py
muzero_baseline/games/simple_grid.py
muzero_baseline/games/spiel.py
muzero_baseline/games/tictactoe.py
muzero_baseline/games/twentyone.py
muzero_baseline-0.4.0.dist-info/LICENSE
muzero_baseline-0.4.0.dist-info/METADATA
muzero_baseline-0.4.0.dist-info/WHEEL
muzero_baseline-0.4.0.dist-info/entry_points.txt
muzero_baseline-0.4.0.dist-info/top_level.txt
muzero_baseline-0.4.0.dist-info/RECORD
