Metadata-Version: 2.1
Name: muzero-baseline
Version: 0.4.0
Summary: Baseline implementation of MuZero agent
Home-page: https://github.com/LeoVS09/muzero-general
Author: LeoVS09
Author-email: leovs010@gmail.com
License: MIT
Platform: UNKNOWN
Classifier: License :: OSI Approved :: MIT License
Classifier: Programming Language :: Python
Classifier: Programming Language :: Python :: 3
Requires-Dist: numpy
Requires-Dist: torch
Requires-Dist: tensorboard
Requires-Dist: gym
Requires-Dist: ray
Requires-Dist: seaborn
Requires-Dist: nevergrad
